rich_rust/__init__.py
rich_rust/rich_rust.abi3.so
rich_rust_py-0.2.0.dist-info/METADATA
rich_rust_py-0.2.0.dist-info/WHEEL
rich_rust_py-0.2.0.dist-info/RECORD
