Metadata-Version: 2.4
Name: rich-rust-py
Version: 0.2.0
Summary: Python bindings for rich-rust
